LICENSE
MANIFEST.in
README.md
pyproject.toml
setup.py
ten_drops/__init__.py
ten_drops/button.py
ten_drops/cli.py
ten_drops/cover.py
ten_drops/drop.py
ten_drops/droplet.py
ten_drops/game.py
ten_drops/notification.py
ten_drops/panel.py
ten_drops.egg-info/PKG-INFO
ten_drops.egg-info/SOURCES.txt
ten_drops.egg-info/dependency_links.txt
ten_drops.egg-info/requires.txt
ten_drops.egg-info/top_level.txt
ten_drops/asset/audio/break.mp3
ten_drops/asset/audio/grow.mp3
ten_drops/asset/audio/hp.mp3
ten_drops/asset/font/FiraCode-Regular.ttf
ten_drops/asset/font/kust.ttf
ten_drops/asset/img/background.png
ten_drops/asset/img/cursor.png
ten_drops/asset/img/game.ico
ten_drops/asset/img/notification.png
ten_drops/asset/img/drop/0.png
ten_drops/asset/img/drop/1.png
ten_drops/asset/img/drop/10.png
ten_drops/asset/img/drop/100.png
ten_drops/asset/img/drop/101.png
ten_drops/asset/img/drop/102.png
ten_drops/asset/img/drop/103.png
ten_drops/asset/img/drop/104.png
ten_drops/asset/img/drop/105.png
ten_drops/asset/img/drop/106.png
ten_drops/asset/img/drop/107.png
ten_drops/asset/img/drop/108.png
ten_drops/asset/img/drop/109.png
ten_drops/asset/img/drop/11.png
ten_drops/asset/img/drop/110.png
ten_drops/asset/img/drop/111.png
ten_drops/asset/img/drop/112.png
ten_drops/asset/img/drop/113.png
ten_drops/asset/img/drop/114.png
ten_drops/asset/img/drop/115.png
ten_drops/asset/img/drop/116.png
ten_drops/asset/img/drop/117.png
ten_drops/asset/img/drop/118.png
ten_drops/asset/img/drop/119.png
ten_drops/asset/img/drop/12.png
ten_drops/asset/img/drop/120.png
ten_drops/asset/img/drop/121.png
ten_drops/asset/img/drop/122.png
ten_drops/asset/img/drop/123.png
ten_drops/asset/img/drop/124.png
ten_drops/asset/img/drop/125.png
ten_drops/asset/img/drop/126.png
ten_drops/asset/img/drop/127.png
ten_drops/asset/img/drop/128.png
ten_drops/asset/img/drop/129.png
ten_drops/asset/img/drop/13.png
ten_drops/asset/img/drop/130.png
ten_drops/asset/img/drop/131.png
ten_drops/asset/img/drop/132.png
ten_drops/asset/img/drop/133.png
ten_drops/asset/img/drop/134.png
ten_drops/asset/img/drop/14.png
ten_drops/asset/img/drop/15.png
ten_drops/asset/img/drop/16.png
