Metadata-Version: 2.1
Name: ten-drops
Version: 1.0.0
Summary: A ten drops game written in pygame-ce.
Home-page: https://github.com/chyok/ten-drops
Author: chyok
Author-email: chyok@hotmail.com
License: MIT
Classifier: License :: OSI Approved :: MIT License
Classifier: Programming Language :: Python
Classifier: Programming Language :: Python :: 3
Classifier: Programming Language :: Python :: 3.8
Classifier: Programming Language :: Python :: 3.9
Classifier: Programming Language :: Python :: 3.10
Classifier: Programming Language :: Python :: 3.11
Classifier: Programming Language :: Python :: 3.12
Classifier: Programming Language :: Python :: Implementation :: CPython
Classifier: Programming Language :: Python :: Implementation :: PyPy
Requires-Python: >=3.8.0
License-File: LICENSE
Requires-Dist: pygame-ce
